{
  "name": "Catalunya - Real F1 Circuit",
  "description": "Circuito real de F1. Longitud: 4.63 km, Ancho medio: 11.2m",
  "total_laps": 5,
  "reference_lap_time": 111.2,
  "width": 11.2,
  "centerline": [
    [
      -0.47,
      0.75
    ],
    [
      -418.72,
      -651.46
    ],
    [
      -441.8,
      -683.99
    ],
    [
      -457.94,
      -695.67
    ],
    [
      -487.2,
      -694.27
    ],
    [
      -535.08,
      -668.36
    ],
    [
      -565.0,
      -667.44
    ],
    [
      -660.04,
      -731.18
    ],
    [
      -712.9,
      -744.08
    ],
    [
      -765.35,
      -729.71
    ],
    [
      -791.9,
      -707.05
    ],
    [
      -809.22,
      -682.7
    ],
    [
      -822.0,
      -650.23
    ],
    [
      -826.59,
      -615.66
    ],
    [
      -822.78,
      -570.88
    ],
    [
      -812.2,
      -532.41
    ],
    [
      -790.24,
      -487.58
    ],
    [
      -671.46,
      -302.4
    ],
    [
      -643.42,
      -275.06
    ],
    [
      -623.94,
      -271.39
    ],
    [
      -604.51,
      -274.88
    ],
    [
      -569.54,
      -302.11
    ],
    [
      -554.33,
      -348.9
    ],
    [
      -557.03,
      -378.81
    ],
    [
      -569.4,
      -411.22
    ],
    [
      -670.71,
      -571.78
    ],
    [
      -671.31,
      -596.29
    ],
    [
      -660.24,
      -612.67
    ],
    [
      -642.0,
      -619.46
    ],
    [
      -622.53,
      -615.66
    ],
    [
      -489.78,
      -557.36
    ],
    [
      -456.04,
      -536.24
    ],
    [
      -417.72,
      -497.0
    ],
    [
      -361.95,
      -414.03
    ],
    [
      -353.77,
      -380.81
    ],
    [
      -362.62,
      -363.17
    ],
    [
      -410.8,
      -327.76
    ],
    [
      -427.65,
      -303.39
    ],
    [
      -498.12,
      -132.31
    ],
    [
      -502.65,
      -102.86
    ],
    [
      -498.73,
      -78.27
    ],
    [
      -482.42,
      -47.56
    ],
    [
      -451.14,
      -23.14
    ],
    [
      -24.8,
      186.27
    ],
    [
      -9.49,
      198.19
    ],
    [
      -2.66,
      217.22
    ],
    [
      -8.02,
      229.73
    ],
    [
      -109.7,
      255.71
    ],
    [
      -124.18,
      254.63
    ],
    [
      -170.06,
      224.41
    ],
    [
      -198.7,
      217.07
    ],
    [
      -227.84,
      222.78
    ],
    [
      -248.62,
      243.72
    ],
    [
      -257.17,
      277.2
    ],
    [
      -245.86,
      309.52
    ],
    [
      -121.94,
      410.53
    ],
    [
      -98.42,
      410.64
    ],
    [
      -5.38,
      342.72
    ],
    [
      8.24,
      344.61
    ],
    [
      29.05,
      365.7
    ],
    [
      43.18,
      362.63
    ],
    [
      117.93,
      312.68
    ],
    [
      140.38,
      274.43
    ],
    [
      142.46,
      239.82
    ],
    [
      132.08,
      206.69
    ],
    [
      2.24,
      4.95
    ]
  ],
  "checkpoints": [
    0,
    3,
    6,
    9,
    13,
    16,
    19,
    23,
    26,
    29,
    33,
    36,
    39,
    42,
    46,
    49,
    52,
    56,
    59,
    62
  ],
  "start_position": [
    -0.47,
    0.75,
    -2.14
  ],
  "pit_entry": [
    -458.32,
    -703.66
  ],
  "pit_exit": [
    -765.73,
    -737.7
  ],
  "pit_lane": [
    [
      -458.32,
      -703.66
    ],
    [
      -489.06,
      -707.07
    ],
    [
      -519.8,
      -710.47
    ],
    [
      -550.54,
      -713.88
    ],
    [
      -581.28,
      -717.28
    ],
    [
      -612.03,
      -720.68
    ],
    [
      -642.77,
      -724.09
    ],
    [
      -673.51,
      -727.49
    ],
    [
      -704.25,
      -730.9
    ],
    [
      -734.99,
      -734.3
    ],
    [
      -765.73,
      -737.7
    ]
  ]
}